mylib033/__init__.py
mylib033-0.1.dist-info/LICENSE.txt
mylib033-0.1.dist-info/METADATA
mylib033-0.1.dist-info/WHEEL
mylib033-0.1.dist-info/top_level.txt
mylib033-0.1.dist-info/RECORD
